Zed_Counter.srcs/sources_1/new/bcd_counter.v
`timescale 1ns / 1ps
//////////////////////////////////////////////////////////////////////////////////
// Company: 
// Engineer: 
// 
// Create Date: 09/07/2025 03:43:54 PM
// Design Name: 
// Module Name: bcd_counter
// Project Name: 
// Target Devices: 
// Tool Versions: 
// Description: 
// 
// Dependencies: 
// 
// Revision:
// Revision 0.01 - File Created
// Additional Comments:
// 
//////////////////////////////////////////////////////////////////////////////////


module bcd_counter #(parameter N = 8)(
    input clk,
    input rst,
    input dir,
    input pause,
    output [N-1:0] out
    );
    
    reg [3:0] ones, tens;

    always @(posedge clk) begin
        if (rst) begin
            ones <= 4'd0;
            tens <= 4'd0;
        end else if (!pause) begin
            if (dir == 0) begin
                // Count up
                if (ones == 9) begin
                    ones <= 0;
                    if (tens == 9)
                        tens <= 0;
                    else
                        tens <= tens + 1;
                end else begin
                    ones <= ones + 1;
                end
            end else begin
                // Count down
                if (ones == 0) begin
                    ones <= 9;
                    if (tens == 0)
                        tens <= 9;
                    else
                        tens <= tens - 1;
                end else begin
                    ones <= ones - 1;
                end
            end
        end
    end

    assign out = {tens, ones};
endmodule

Zed_Counter.srcs/sim_1/new/bcd_counter_tb.v
`timescale 1ns / 1ps
//////////////////////////////////////////////////////////////////////////////////
// Company: 
// Engineer: 
// 
// Create Date: 09/13/2025 01:25:49 PM
// Design Name: 
// Module Name: bcd_counter_tb
// Project Name: 
// Target Devices: 
// Tool Versions: 
// Description: 
// 
// Dependencies: 
// 
// Revision:
// Revision 0.01 - File Created
// Additional Comments:
// 
//////////////////////////////////////////////////////////////////////////////////


module bcd_counter_tb;

    // Parameters
    parameter N = 8;

    // Testbench signals
    reg clk;
    reg rst;
    reg dir;
    reg pause;
    wire [N-1:0] out;

    // Instantiate DUT
    bcd_counter #(N) uut (
        .clk(clk),
        .rst(rst),
        .dir(dir),
        .pause(pause),
        .out(out)
    );

    // Clock generation: 10 ns period
    always #5 clk = ~clk;

    initial begin
        // VCD dump for GTKWave/DVE
        $dumpfile("bcd_counter_tb.vcd");
        $dumpvars(0, bcd_counter_tb);

        // Console monitor (show BCD digits separately)
        $monitor("T=%0t | rst=%b pause=%b dir=%b | tens=%0d ones=%0d out=%b",
                  $time, rst, pause, dir, out[7:4], out[3:0], out);

        // Initialize signals
        clk   = 0;
        rst   = 1;   // reset active
        dir   = 0;   // count up
        pause = 0;

        // Hold reset
        #20 rst = 0;

        // Count up (00 ? 15, etc.)
        #160;

        // Pause counter
        pause = 1;
        #40;
        pause = 0;

        // Switch to count down
        dir = 1;
        #160;

        // Reset again
        rst = 1;
        #20 rst = 0;

        // Count up again
        dir = 0;
        #100;

        // End simulation
        $finish;
    end
endmodule

Zed_Counter.sim/sim_1/behav/xsim/bcd_counter_tb.vcd
$date
   Sat Sep 13 13:28:30 2025
$end

$version
  2023.2
  $dumpfile ("bcd_counter_tb.vcd") 
$end

$timescale
  1ps
$end

$scope module bcd_counter_tb $end
$var reg 1 ! clk $end
$var reg 1 " rst $end
$var reg 1 # dir $end
$var reg 1 $ pause $end
$var wire 8 % out [7:0] $end
$scope module uut $end
$var wire 1 & clk $end
$var wire 1 ' rst $end
$var wire 1 ( dir $end
$var wire 1 ) pause $end
$var wire 8 % out [7:0] $end
$var reg 4 * ones [3:0] $end
$var reg 4 + tens [3:0] $end
$upscope $end
$upscope $end
$enddefinitions $end

#0
$dumpvars
0!
1"
0#
0$
b0 %
0&
1'
0(
0)
b0 *
b0 +
$end

#5000
1!
1&

#10000
0!
0&

#15000
1!
1&

#20000
0!
0"
0&
0'

#25000
1!
b1 %
1&
b1 *

#30000
0!
0&

#35000
1!
b10 %
1&
b10 *

#40000
0!
0&

#45000
1!
b11 %
1&
b11 *

#50000
0!
0&

#55000
1!
b100 %
1&
b100 *

#60000
0!
0&

#65000
1!
b101 %
1&
b101 *

#70000
0!
0&

#75000
1!
b110 %
1&
b110 *

#80000
0!
0&

#85000
1!
b111 %
1&
b111 *

#90000
0!
0&

#95000
1!
b1000 %
1&
b1000 *

#100000
0!
0&

#105000
1!
b1001 %
1&
b1001 *

#110000
0!
0&

#115000
1!
b10000 %
1&
b0 *
b1 +

#120000
0!
0&

#125000
1!
b10001 %
1&
b1 *

#130000
0!
0&

#135000
1!
b10010 %
1&
b10 *

#140000
0!
0&

#145000
1!
b10011 %
1&
b11 *

#150000
0!
0&

#155000
1!
b10100 %
1&
b100 *

#160000
0!
0&

#165000
1!
b10101 %
1&
b101 *

#170000
0!
0&

#175000
1!
b10110 %
1&
b110 *

#180000
0!
1$
0&
1)

#185000
1!
1&

#190000
0!
0&

#195000
1!
1&

#200000
0!
0&

#205000
1!
1&

#210000
0!
0&

#215000
1!
1&

#220000
0!
1#
0$
0&
1(
0)

#225000
1!
b10101 %
1&
b101 *

#230000
0!
0&

#235000
1!
b10100 %
1&
b100 *

#240000
0!
0&

#245000
1!
b10011 %
1&
b11 *

#250000
0!
0&

#255000
1!
b10010 %
1&
b10 *

#260000
0!
0&

#265000
1!
b10001 %
1&
b1 *

#270000
0!
0&

#275000
1!
b10000 %
1&
b0 *

#280000
0!
0&

#285000
1!
b1001 %
1&
b1001 *
b0 +

#290000
0!
0&

#295000
1!
b1000 %
1&
b1000 *

#300000
0!
0&

#305000
1!
b111 %
1&
b111 *

#310000
0!
0&

#315000
1!
b110 %
1&
b110 *

#320000
0!
0&

#325000
1!
b101 %
1&
b101 *

#330000
0!
0&

#335000
1!
b100 %
1&
b100 *

#340000
0!
0&

#345000
1!
b11 %
1&
b11 *

#350000
0!
0&

#355000
1!
b10 %
1&
b10 *

#360000
0!
0&

#365000
1!
b1 %
1&
b1 *

#370000
0!
0&

#375000
1!
b0 %
1&
b0 *

#380000
0!
1"
0&
1'

#385000
1!
1&

#390000
0!
0&

#395000
1!
1&

#400000
0!
0"
0#
0&
0'
0(

#405000
1!
b1 %
1&
b1 *

#410000
0!
0&

#415000
1!
b10 %
1&
b10 *

#420000
0!
0&

#425000
1!
b11 %
1&
b11 *

#430000
0!
0&

#435000
1!
b100 %
1&
b100 *

#440000
0!
0&

#445000
1!
b101 %
1&
b101 *

#450000
0!
0&

#455000
1!
b110 %
1&
b110 *

#460000
0!
0&

#465000
1!
b111 %
1&
b111 *

#470000
0!
0&

#475000
1!
b1000 %
1&
b1000 *

#480000
0!
0&

#485000
1!
b1001 %
1&
b1001 *

#490000
0!
0&

#495000
1!
b10000 %
1&
b0 *
b1 +
