Zed_Counter.srcs/sources_1/new/binary_up_counter.v
`timescale 1ns / 1ps
//////////////////////////////////////////////////////////////////////////////////
// Company: 
// Engineer: 
// 
// Create Date: 09/05/2025 01:33:51 PM
// Design Name: 
// Module Name: binary_up_counter
// Project Name: 
// Target Devices: 
// Tool Versions: 
// Description: 
// 
// Dependencies: 
// 
// Revision:
// Revision 0.01 - File Created
// Additional Comments:
// 
//////////////////////////////////////////////////////////////////////////////////


module binary_up_counter #(parameter N = 8) (
    input clk,
    input rst,
    input dir,
    input pause,
    output reg [N-1:0] count
    );
    
    always @(posedge clk or posedge rst) begin
        if(rst) begin
            count <= 0;
            end
        else if(!pause) begin
            if (dir == 0)
                count <= count + 1;
            else
                count <= count  - 1;
        end
    end
endmodule

Zed_Counter.srcs/sim_1/new/binary_counter_tb.v
`timescale 1ns / 1ps
//////////////////////////////////////////////////////////////////////////////////
// Company: 
// Engineer: 
// 
// Create Date: 09/13/2025 01:08:50 PM
// Design Name: 
// Module Name: binary_counter_tb
// Project Name: 
// Target Devices: 
// Tool Versions: 
// Description: 
// 
// Dependencies: 
// 
// Revision:
// Revision 0.01 - File Created
// Additional Comments:
// 
//////////////////////////////////////////////////////////////////////////////////


`timescale 1ns/1ps

module binary_counter_tb;

    // Parameters
    parameter N = 8;

    // Testbench signals
    reg clk;
    reg rst;
    reg dir;
    reg pause;
    wire [N-1:0] count;

    // Instantiate DUT
    binary_up_counter #(N) uut (
        .clk(clk),
        .rst(rst),
        .dir(dir),
        .pause(pause),
        .count(count)
    );

    // Clock generation: 10 ns period
    always #5 clk = ~clk;

    initial begin
        // Enable waveform dump
        $dumpfile("binary_counter_tb.vcd");
        $dumpvars(0, binary_counter_tb);

        // Display all activity in console
        $monitor("T=%0t | rst=%b pause=%b dir=%b count=%0d", 
                  $time, rst, pause, dir, count);

        // Initialize
        clk   = 0;
        rst   = 1;
        dir   = 0;   // up
        pause = 0;

        // Hold reset
        #20 rst = 0;

        // Count up
        #100;

        // Pause
        pause = 1; 
        #40;
        pause = 0;

        // Count down
        dir = 1;
        #100;

        // Reset again
        rst = 1; 
        #20 rst = 0;

        // Count up again
        dir = 0;
        #80;

        // End
        $finish;
    end
endmodule

Zed_Counter.sim/sim_1/behav/xsim/binary_counter_tb.vcd
$date
   Sat Sep 13 13:11:24 2025
$end

$version
  2023.2
  $dumpfile ("binary_counter_tb.vcd") 
$end

$timescale
  1ps
$end

$scope module binary_counter_tb $end
$var reg 1 ! clk $end
$var reg 1 " rst $end
$var reg 1 # dir $end
$var reg 1 $ pause $end
$var wire 8 % count [7:0] $end
$scope module uut $end
$var wire 1 & clk $end
$var wire 1 ' rst $end
$var wire 1 ( dir $end
$var wire 1 ) pause $end
$var reg 8 * count [7:0] $end
$upscope $end
$upscope $end
$enddefinitions $end

#0
$dumpvars
0!
1"
0#
0$
b0 %
0&
1'
0(
0)
b0 *
$end

#5000
1!
1&

#10000
0!
0&

#15000
1!
1&

#20000
0!
0"
0&
0'

#25000
1!
b1 %
1&
b1 *

#30000
0!
0&

#35000
1!
b10 %
1&
b10 *

#40000
0!
0&

#45000
1!
b11 %
1&
b11 *

#50000
0!
0&

#55000
1!
b100 %
1&
b100 *

#60000
0!
0&

#65000
1!
b101 %
1&
b101 *

#70000
0!
0&

#75000
1!
b110 %
1&
b110 *

#80000
0!
0&

#85000
1!
b111 %
1&
b111 *

#90000
0!
0&

#95000
1!
b1000 %
1&
b1000 *

#100000
0!
0&

#105000
1!
b1001 %
1&
b1001 *

#110000
0!
0&

#115000
1!
b1010 %
1&
b1010 *

#120000
0!
1$
0&
1)

#125000
1!
1&

#130000
0!
0&

#135000
1!
1&

#140000
0!
0&

#145000
1!
1&

#150000
0!
0&

#155000
1!
1&

#160000
0!
1#
0$
0&
1(
0)

#165000
1!
b1001 %
1&
b1001 *

#170000
0!
0&

#175000
1!
b1000 %
1&
b1000 *

#180000
0!
0&

#185000
1!
b111 %
1&
b111 *

#190000
0!
0&

#195000
1!
b110 %
1&
b110 *

#200000
0!
0&

#205000
1!
b101 %
1&
b101 *

#210000
0!
0&

#215000
1!
b100 %
1&
b100 *

#220000
0!
0&

#225000
1!
b11 %
1&
b11 *

#230000
0!
0&

#235000
1!
b10 %
1&
b10 *

#240000
0!
0&

#245000
1!
b1 %
1&
b1 *

#250000
0!
0&

#255000
1!
b0 %
1&
b0 *

#260000
0!
1"
0&
1'

#265000
1!
1&

#270000
0!
0&

#275000
1!
1&

#280000
0!
0"
0#
0&
0'
0(

#285000
1!
b1 %
1&
b1 *

#290000
0!
0&

#295000
1!
b10 %
1&
b10 *

#300000
0!
0&

#305000
1!
b11 %
1&
b11 *

#310000
0!
0&

#315000
1!
b100 %
1&
b100 *

#320000
0!
0&

#325000
1!
b101 %
1&
b101 *

#330000
0!
0&

#335000
1!
b110 %
1&
b110 *

#340000
0!
0&

#345000
1!
b111 %
1&
b111 *

#350000
0!
0&

#355000
1!
b1000 %
1&
b1000 *
