Zed_Counter.srcs/sources_1/new/fibonacci_counter.v
`timescale 1ns / 1ps
//////////////////////////////////////////////////////////////////////////////////
// Company: 
// Engineer: 
// 
// Create Date: 09/07/2025 03:37:49 PM
// Design Name: 
// Module Name: fibonacci_counter
// Project Name: 
// Target Devices: 
// Tool Versions: 
// Description: 
// 
// Dependencies: 
// 
// Revision:
// Revision 0.01 - File Created
// Additional Comments:
// 
//////////////////////////////////////////////////////////////////////////////////


module fibonacci_counter #(parameter N = 8)(
    input clk,
    input rst,
    input dir,
    input pause,
    output reg [N-1:0] out
    );
    
    reg [7:0] prev, curr;

    always @(posedge clk or posedge rst) begin
        if (rst) begin
            prev <= 8'b0;     
            curr <= 8'b1;
            out  <= 8'b0;
        end else if (!pause) begin
            if (dir == 0) begin
                // Forward Fibonacci
                out  <= prev;
                curr <= prev + curr;
                prev <= curr;
            end else begin
                // Reverse Fibonacci
                out  <= prev;
                prev <= curr - prev;
                prev <= out;
            end
        end
    end
endmodule

Zed_Counter.srcs/sim_1/new/fibonacci_counter_tb.v
`timescale 1ns / 1ps
//////////////////////////////////////////////////////////////////////////////////
// Company: 
// Engineer: 
// 
// Create Date: 09/13/2025 01:23:25 PM
// Design Name: 
// Module Name: fibonacci_counter_tb
// Project Name: 
// Target Devices: 
// Tool Versions: 
// Description: 
// 
// Dependencies: 
// 
// Revision:
// Revision 0.01 - File Created
// Additional Comments:
// 
//////////////////////////////////////////////////////////////////////////////////


module fibonacci_counter_tb;

    // Parameters
    parameter N = 8;

    // Testbench signals
    reg clk;
    reg rst;
    reg dir;
    reg pause;
    wire [N-1:0] out;

    // Instantiate DUT
    fibonacci_counter #(N) uut (
        .clk(clk),
        .rst(rst),
        .dir(dir),
        .pause(pause),
        .out(out)
    );

    // Clock generation: 10 ns period
    always #5 clk = ~clk;

    initial begin
        // VCD dump for GTKWave/DVE
        $dumpfile("fibonacci_counter_tb.vcd");
        $dumpvars(0, fibonacci_counter_tb);

        // Console monitoring
        $monitor("T=%0t | rst=%b pause=%b dir=%b out=%0d", 
                  $time, rst, pause, dir, out);

        // Initialize signals
        clk   = 0;
        rst   = 1;   // reset active
        dir   = 0;   // forward Fibonacci
        pause = 0;

        // Hold reset
        #20 rst = 0;

        // Run forward Fibonacci sequence
        #200;

        // Pause sequence
        pause = 1;
        #40;
        pause = 0;

        // Switch to "reverse" Fibonacci
        dir = 1;
        #100;

        // Reset again
        rst = 1;
        #20 rst = 0;

        // Forward again
        dir = 0;
        #120;

        // End simulation
        $finish;
    end
endmodule

Zed_Counter.sim/sim_1/behav/xsim/fibonacci_counter_tb.vcd
$date
   Sat Sep 13 13:24:48 2025
$end

$version
  2023.2
  $dumpfile ("fibonacci_counter_tb.vcd") 
$end

$timescale
  1ps
$end

$scope module fibonacci_counter_tb $end
$var reg 1 ! clk $end
$var reg 1 " rst $end
$var reg 1 # dir $end
$var reg 1 $ pause $end
$var wire 8 % out [7:0] $end
$scope module uut $end
$var wire 1 & clk $end
$var wire 1 ' rst $end
$var wire 1 ( dir $end
$var wire 1 ) pause $end
$var reg 8 * out [7:0] $end
$var reg 8 + prev [7:0] $end
$var reg 8 , curr [7:0] $end
$upscope $end
$upscope $end
$enddefinitions $end

#0
$dumpvars
0!
1"
0#
0$
b0 %
0&
1'
0(
0)
b0 *
b0 +
b1 ,
$end

#5000
1!
1&

#10000
0!
0&

#15000
1!
1&

#20000
0!
0"
0&
0'

#25000
1!
1&
b1 +

#30000
0!
0&

#35000
1!
b1 %
1&
b1 *
b10 ,

#40000
0!
0&

#45000
1!
1&
b10 +
b11 ,

#50000
0!
0&

#55000
1!
b10 %
1&
b10 *
b11 +
b101 ,

#60000
0!
0&

#65000
1!
b11 %
1&
b11 *
b101 +
b1000 ,

#70000
0!
0&

#75000
1!
b101 %
1&
b101 *
b1000 +
b1101 ,

#80000
0!
0&

#85000
1!
b1000 %
1&
b1000 *
b1101 +
b10101 ,

#90000
0!
0&

#95000
1!
b1101 %
1&
b1101 *
b10101 +
b100010 ,

#100000
0!
0&

#105000
1!
b10101 %
1&
b10101 *
b100010 +
b110111 ,

#110000
0!
0&

#115000
1!
b100010 %
1&
b100010 *
b110111 +
b1011001 ,

#120000
0!
0&

#125000
1!
b110111 %
1&
b110111 *
b1011001 +
b10010000 ,

#130000
0!
0&

#135000
1!
b1011001 %
1&
b1011001 *
b10010000 +
b11101001 ,

#140000
0!
0&

#145000
1!
b10010000 %
1&
b10010000 *
b11101001 +
b1111001 ,

#150000
0!
0&

#155000
1!
b11101001 %
1&
b11101001 *
b1111001 +
b1100010 ,

#160000
0!
0&

#165000
1!
b1111001 %
1&
b1111001 *
b1100010 +
b11011011 ,

#170000
0!
0&

#175000
1!
b1100010 %
1&
b1100010 *
b11011011 +
b111101 ,

#180000
0!
0&

#185000
1!
b11011011 %
1&
b11011011 *
b111101 +
b11000 ,

#190000
0!
0&

#195000
1!
b111101 %
1&
b111101 *
b11000 +
b1010101 ,

#200000
0!
0&

#205000
1!
b11000 %
1&
b11000 *
b1010101 +
b1101101 ,

#210000
0!
0&

#215000
1!
b1010101 %
1&
b1010101 *
b1101101 +
b11000010 ,

#220000
0!
1$
0&
1)

#225000
1!
1&

#230000
0!
0&

#235000
1!
1&

#240000
0!
0&

#245000
1!
1&

#250000
0!
0&

#255000
1!
1&

#260000
0!
1#
0$
0&
1(
0)

#265000
1!
b1101101 %
1&
b1101101 *
b1010101 +

#270000
0!
0&

#275000
1!
b1010101 %
1&
b1010101 *
b1101101 +

#280000
0!
0&

#285000
1!
b1101101 %
1&
b1101101 *
b1010101 +

#290000
0!
0&

#295000
1!
b1010101 %
1&
b1010101 *
b1101101 +

#300000
0!
0&

#305000
1!
b1101101 %
1&
b1101101 *
b1010101 +

#310000
0!
0&

#315000
1!
b1010101 %
1&
b1010101 *
b1101101 +

#320000
0!
0&

#325000
1!
b1101101 %
1&
b1101101 *
b1010101 +

#330000
0!
0&

#335000
1!
b1010101 %
1&
b1010101 *
b1101101 +

#340000
0!
0&

#345000
1!
b1101101 %
1&
b1101101 *
b1010101 +

#350000
0!
0&

#355000
1!
b1010101 %
1&
b1010101 *
b1101101 +

#360000
0!
1"
b0 %
0&
1'
b0 *
b0 +
b1 ,

#365000
1!
1&

#370000
0!
0&

#375000
1!
1&

#380000
0!
0"
0#
0&
0'
0(

#385000
1!
1&
b1 +

#390000
0!
0&

#395000
1!
b1 %
1&
b1 *
b10 ,

#400000
0!
0&

#405000
1!
1&
b10 +
b11 ,

#410000
0!
0&

#415000
1!
b10 %
1&
b10 *
b11 +
b101 ,

#420000
0!
0&

#425000
1!
b11 %
1&
b11 *
b101 +
b1000 ,

#430000
0!
0&

#435000
1!
b101 %
1&
b101 *
b1000 +
b1101 ,

#440000
0!
0&

#445000
1!
b1000 %
1&
b1000 *
b1101 +
b10101 ,

#450000
0!
0&

#455000
1!
b1101 %
1&
b1101 *
b10101 +
b100010 ,

#460000
0!
0&

#465000
1!
b10101 %
1&
b10101 *
b100010 +
b110111 ,

#470000
0!
0&

#475000
1!
b100010 %
1&
b100010 *
b110111 +
b1011001 ,

#480000
0!
0&

#485000
1!
b110111 %
1&
b110111 *
b1011001 +
b10010000 ,

#490000
0!
0&

#495000
1!
b1011001 %
1&
b1011001 *
b10010000 +
b11101001 ,
