Zed_Counter.srcs/sources_1/new/johnson_counter.v
`timescale 1ns / 1ps
//////////////////////////////////////////////////////////////////////////////////
// Company: 
// Engineer: 
// 
// Create Date: 09/06/2025 03:46:52 PM
// Design Name: 
// Module Name: johnson_counter
// Project Name: 
// Target Devices: 
// Tool Versions: 
// Description: 
// 
// Dependencies: 
// 
// Revision:
// Revision 0.01 - File Created
// Additional Comments:
// 
//////////////////////////////////////////////////////////////////////////////////


module johnson_counter #(parameter N = 8)(
    input clk,
    input rst,
    input dir,
    input pause,
    output reg [N-1:0] out
    );
    
    always @(posedge clk or posedge rst) begin
        if(rst)
            out <= 8'b0000_0000;
        else if (!pause) begin
            if(dir == 0) begin
                out <= {out[6:0], ~out[7]};
            end else begin
                out <= {~out[0], out[7:1]};
            end
        end
    end 
endmodule

Zed_Counter.srcs/sources_1/new/johnson_counter_tb.v
`timescale 1ns / 1ps
//////////////////////////////////////////////////////////////////////////////////
// Company: 
// Engineer: 
// 
// Create Date: 09/13/2025 01:17:00 PM
// Design Name: 
// Module Name: johnson_counter_tb
// Project Name: 
// Target Devices: 
// Tool Versions: 
// Description: 
// 
// Dependencies: 
// 
// Revision:
// Revision 0.01 - File Created
// Additional Comments:
// 
//////////////////////////////////////////////////////////////////////////////////


module johnson_counter_tb;

    // Parameters
    parameter N = 8;

    // Testbench signals
    reg clk;
    reg rst;
    reg dir;
    reg pause;
    wire [N-1:0] out;

    // Instantiate DUT
    johnson_counter #(N) uut (
        .clk(clk),
        .rst(rst),
        .dir(dir),
        .pause(pause),
        .out(out)
    );

    // Clock generation: 10 ns period
    always #5 clk = ~clk;

    initial begin
        // VCD dump for GTKWave/DVE
        $dumpfile("johnson_counter_tb.vcd");
        $dumpvars(0, johnson_counter_tb);

        // Console monitor
        $monitor("T=%0t | rst=%b pause=%b dir=%b out=%b",
                  $time, rst, pause, dir, out);

        // Init signals
        clk   = 0;
        rst   = 1;   // assert reset
        dir   = 0;   // shift left first
        pause = 0;

        // Hold reset
        #20 rst = 0;

        // Run forward (dir=0)
        #120;

        // Pause counter
        pause = 1;
        #40;
        pause = 0;

        // Reverse direction (dir=1)
        dir = 1;
        #120;

        // Reset again
        rst = 1;
        #20 rst = 0;

        // Forward again
        dir = 0;
        #80;

        // End simulation
        $finish;
    end
endmodule

Zed_Counter.sim/sim_1/behav/xsim/johnson_counter_tb.vcd
$date
   Sat Sep 13 13:18:52 2025
$end

$version
  2023.2
  $dumpfile ("johnson_counter_tb.vcd") 
$end

$timescale
  1ps
$end

$scope module johnson_counter_tb $end
$var reg 1 ! clk $end
$var reg 1 " rst $end
$var reg 1 # dir $end
$var reg 1 $ pause $end
$var wire 8 % out [7:0] $end
$scope module uut $end
$var wire 1 & clk $end
$var wire 1 ' rst $end
$var wire 1 ( dir $end
$var wire 1 ) pause $end
$var reg 8 * out [7:0] $end
$upscope $end
$upscope $end
$enddefinitions $end

#0
$dumpvars
0!
1"
0#
0$
b0 %
0&
1'
0(
0)
b0 *
$end

#5000
1!
1&

#10000
0!
0&

#15000
1!
1&

#20000
0!
0"
0&
0'

#25000
1!
b1 %
1&
b1 *

#30000
0!
0&

#35000
1!
b11 %
1&
b11 *

#40000
0!
0&

#45000
1!
b111 %
1&
b111 *

#50000
0!
0&

#55000
1!
b1111 %
1&
b1111 *

#60000
0!
0&

#65000
1!
b11111 %
1&
b11111 *

#70000
0!
0&

#75000
1!
b111111 %
1&
b111111 *

#80000
0!
0&

#85000
1!
b1111111 %
1&
b1111111 *

#90000
0!
0&

#95000
1!
b11111111 %
1&
b11111111 *

#100000
0!
0&

#105000
1!
b11111110 %
1&
b11111110 *

#110000
0!
0&

#115000
1!
b11111100 %
1&
b11111100 *

#120000
0!
0&

#125000
1!
b11111000 %
1&
b11111000 *

#130000
0!
0&

#135000
1!
b11110000 %
1&
b11110000 *

#140000
0!
1$
0&
1)

#145000
1!
1&

#150000
0!
0&

#155000
1!
1&

#160000
0!
0&

#165000
1!
1&

#170000
0!
0&

#175000
1!
1&

#180000
0!
1#
0$
0&
1(
0)

#185000
1!
b11111000 %
1&
b11111000 *

#190000
0!
0&

#195000
1!
b11111100 %
1&
b11111100 *

#200000
0!
0&

#205000
1!
b11111110 %
1&
b11111110 *

#210000
0!
0&

#215000
1!
b11111111 %
1&
b11111111 *

#220000
0!
0&

#225000
1!
b1111111 %
1&
b1111111 *

#230000
0!
0&

#235000
1!
b111111 %
1&
b111111 *

#240000
0!
0&

#245000
1!
b11111 %
1&
b11111 *

#250000
0!
0&

#255000
1!
b1111 %
1&
b1111 *

#260000
0!
0&

#265000
1!
b111 %
1&
b111 *

#270000
0!
0&

#275000
1!
b11 %
1&
b11 *

#280000
0!
0&

#285000
1!
b1 %
1&
b1 *

#290000
0!
0&

#295000
1!
b0 %
1&
b0 *

#300000
0!
1"
0&
1'

#305000
1!
1&

#310000
0!
0&

#315000
1!
1&

#320000
0!
0"
0#
0&
0'
0(

#325000
1!
b1 %
1&
b1 *

#330000
0!
0&

#335000
1!
b11 %
1&
b11 *

#340000
0!
0&

#345000
1!
b111 %
1&
b111 *

#350000
0!
0&

#355000
1!
b1111 %
1&
b1111 *

#360000
0!
0&

#365000
1!
b11111 %
1&
b11111 *

#370000
0!
0&

#375000
1!
b111111 %
1&
b111111 *

#380000
0!
0&

#385000
1!
b1111111 %
1&
b1111111 *

#390000
0!
0&

#395000
1!
b11111111 %
1&
b11111111 *
