Zed_Counter.srcs/sources_1/new/ring_counter.v
`timescale 1ns / 1ps
//////////////////////////////////////////////////////////////////////////////////
// Company: 
// Engineer: 
// 
// Create Date: 09/05/2025 03:45:07 PM
// Design Name: 
// Module Name: ring_counter
// Project Name: 
// Target Devices: 
// Tool Versions: 
// Description: 
// 
// Dependencies: 
// 
// Revision:
// Revision 0.01 - File Created
// Additional Comments:
// 
//////////////////////////////////////////////////////////////////////////////////


module ring_counter #(parameter N = 8)(
    input clk,
    input rst,
    input dir,
    input pause,
    output reg [N-1:0] out
    );
    
    always @(posedge clk or posedge rst) begin
        if(rst)
            out <= 8'b0000_0001;
         else if (!pause) begin
            if(dir == 0) begin
                out <= (out << 1) | (out >> 7);
            end else begin
                out <= (out >> 1) | (out << 7);
            end
        end
    end   
endmodule

Zed_Counter.srcs/sim_1/new/ring_counter_tb.v
`timescale 1ns / 1ps
//////////////////////////////////////////////////////////////////////////////////
// Company: 
// Engineer: 
// 
// Create Date: 09/13/2025 01:12:56 PM
// Design Name: 
// Module Name: ring_counter_tb
// Project Name: 
// Target Devices: 
// Tool Versions: 
// Description: 
// 
// Dependencies: 
// 
// Revision:
// Revision 0.01 - File Created
// Additional Comments:
// 
//////////////////////////////////////////////////////////////////////////////////


module ring_counter_tb;

    // Parameters
    parameter N = 8;

    // Testbench signals
    reg clk;
    reg rst;
    reg dir;
    reg pause;
    wire [N-1:0] out;

    // Instantiate DUT
    ring_counter #(N) uut (
        .clk(clk),
        .rst(rst),
        .dir(dir),
        .pause(pause),
        .out(out)
    );

    // Clock generation: 10 ns period
    always #5 clk = ~clk;

    initial begin
        // VCD waveform dump (for GTKWave or DVE)
        $dumpfile("ring_counter_tb.vcd");
        $dumpvars(0, ring_counter_tb);

        // Console monitor
        $monitor("T=%0t | rst=%b pause=%b dir=%b out=%b", 
                  $time, rst, pause, dir, out);

        // Init signals
        clk   = 0;
        rst   = 1;   // reset active
        dir   = 0;   // rotate left
        pause = 0;

        // Hold reset
        #20 rst = 0;

        // Let it rotate left for a few cycles
        #100;

        // Pause
        pause = 1;
        #40;
        pause = 0;

        // Change direction ? rotate right
        dir = 1;
        #100;

        // Reset again
        rst = 1;
        #20 rst = 0;

        // Rotate left again
        dir = 0;
        #80;

        // End
        $finish;
    end
endmodule

Zed_Counter.sim/sim_1/behav/xsim/ring_counter_tb.vcd
$date
   Sat Sep 13 13:14:40 2025
$end

$version
  2023.2
  $dumpfile ("ring_counter_tb.vcd") 
$end

$timescale
  1ps
$end

$scope module ring_counter_tb $end
$var reg 1 ! clk $end
$var reg 1 " rst $end
$var reg 1 # dir $end
$var reg 1 $ pause $end
$var wire 8 % out [7:0] $end
$scope module uut $end
$var wire 1 & clk $end
$var wire 1 ' rst $end
$var wire 1 ( dir $end
$var wire 1 ) pause $end
$var reg 8 * out [7:0] $end
$upscope $end
$upscope $end
$enddefinitions $end

#0
$dumpvars
0!
1"
0#
0$
b1 %
0&
1'
0(
0)
b1 *
$end

#5000
1!
1&

#10000
0!
0&

#15000
1!
1&

#20000
0!
0"
0&
0'

#25000
1!
b10 %
1&
b10 *

#30000
0!
0&

#35000
1!
b100 %
1&
b100 *

#40000
0!
0&

#45000
1!
b1000 %
1&
b1000 *

#50000
0!
0&

#55000
1!
b10000 %
1&
b10000 *

#60000
0!
0&

#65000
1!
b100000 %
1&
b100000 *

#70000
0!
0&

#75000
1!
b1000000 %
1&
b1000000 *

#80000
0!
0&

#85000
1!
b10000000 %
1&
b10000000 *

#90000
0!
0&

#95000
1!
b1 %
1&
b1 *

#100000
0!
0&

#105000
1!
b10 %
1&
b10 *

#110000
0!
0&

#115000
1!
b100 %
1&
b100 *

#120000
0!
1$
0&
1)

#125000
1!
1&

#130000
0!
0&

#135000
1!
1&

#140000
0!
0&

#145000
1!
1&

#150000
0!
0&

#155000
1!
1&

#160000
0!
1#
0$
0&
1(
0)

#165000
1!
b10 %
1&
b10 *

#170000
0!
0&

#175000
1!
b1 %
1&
b1 *

#180000
0!
0&

#185000
1!
b10000000 %
1&
b10000000 *

#190000
0!
0&

#195000
1!
b1000000 %
1&
b1000000 *

#200000
0!
0&

#205000
1!
b100000 %
1&
b100000 *

#210000
0!
0&

#215000
1!
b10000 %
1&
b10000 *

#220000
0!
0&

#225000
1!
b1000 %
1&
b1000 *

#230000
0!
0&

#235000
1!
b100 %
1&
b100 *

#240000
0!
0&

#245000
1!
b10 %
1&
b10 *

#250000
0!
0&

#255000
1!
b1 %
1&
b1 *

#260000
0!
1"
0&
1'

#265000
1!
1&

#270000
0!
0&

#275000
1!
1&

#280000
0!
0"
0#
0&
0'
0(

#285000
1!
b10 %
1&
b10 *

#290000
0!
0&

#295000
1!
b100 %
1&
b100 *

#300000
0!
0&

#305000
1!
b1000 %
1&
b1000 *

#310000
0!
0&

#315000
1!
b10000 %
1&
b10000 *

#320000
0!
0&

#325000
1!
b100000 %
1&
b100000 *

#330000
0!
0&

#335000
1!
b1000000 %
1&
b1000000 *

#340000
0!
0&

#345000
1!
b10000000 %
1&
b10000000 *

#350000
0!
0&

#355000
1!
b1 %
1&
b1 *
